permedcoe/__init__.py
permedcoe/__main__.py
permedcoe/base.py
permedcoe/bb.py
permedcoe/core/__init__.py
permedcoe/core/building_block.py
permedcoe/core/constants.py
permedcoe/core/decorators.py
permedcoe/core/environment.py
permedcoe/core/functions.py
permedcoe/templates/application/NextFlow/NextFlow.nf
permedcoe/templates/application/NextFlow/launch.sh
permedcoe/templates/application/PyCOMPSs/app.py
permedcoe/templates/application/PyCOMPSs/launch.sh
permedcoe/templates/application/PyCOMPSs/launch_without_pycompss.sh
permedcoe/templates/application/SnakeMake/Snakefile
permedcoe/templates/application/SnakeMake/launch.sh
permedcoe/templates/building_block/skeleton_BB/README.md
permedcoe/templates/building_block/skeleton_BB/build.sh
permedcoe/templates/building_block/skeleton_BB/clean.sh
permedcoe/templates/building_block/skeleton_BB/install.sh
permedcoe/templates/building_block/skeleton_BB/install_sc.sh
permedcoe/templates/building_block/skeleton_BB/pyproject.toml
permedcoe/templates/building_block/skeleton_BB/setup.cfg
permedcoe/templates/building_block/skeleton_BB/setup.py
permedcoe/templates/building_block/skeleton_BB/uninstall.sh
permedcoe/templates/building_block/skeleton_BB/container/create_container.sh
permedcoe/templates/building_block/skeleton_BB/container/sample.def
permedcoe/templates/building_block/skeleton_BB/src/bb/__init__.py
permedcoe/templates/building_block/skeleton_BB/src/bb/__main__.py
permedcoe/templates/building_block/skeleton_BB/src/bb/definition.json
permedcoe/templates/building_block/skeleton_BB/src/bb/definitions.py
permedcoe/templates/building_block/skeleton_BB/src/bb/main.py
permedcoe/templates/building_block/skeleton_BB/src/bb/assets/my_binary.sh
permedcoe/utils/__init__.py
permedcoe/utils/arguments.py
permedcoe/utils/artifact.py
permedcoe/utils/environ.py
permedcoe/utils/exceptions.py
permedcoe/utils/executor.py
permedcoe/utils/log.py
permedcoe/utils/preproc.py
permedcoe/utils/user_arguments.py
permedcoe-0.0.11.dist-info/METADATA
permedcoe-0.0.11.dist-info/WHEEL
permedcoe-0.0.11.dist-info/entry_points.txt
permedcoe-0.0.11.dist-info/top_level.txt
permedcoe-0.0.11.dist-info/RECORD
