Metadata-Version: 2.1
Name: permedcoe
Version: 0.0.11
Summary: This package provides the common interface for the Building Blocks.
Home-page: https://github.com/PerMedCoE/permedcoe
Author: PerMedCoE Project
Author-email: infoPerMedCoE@bsc.es
Project-URL: Bug Reports, https://github.com/PerMedCoE/permedcoe/issues
Project-URL: Source, https://github.com/PerMedCoE/permedcoe
Keywords: PerMedCoE
Classifier: Development Status :: 5 - Production/Stable
Classifier: License :: OSI Approved :: Apache Software License
Classifier: Intended Audience :: Science/Research
Classifier: Operating System :: Unix
Classifier: Operating System :: POSIX :: Linux
Classifier: Operating System :: MacOS
Classifier: Topic :: Scientific/Engineering :: Bio-Informatics
Classifier: Programming Language :: Python :: 3
Classifier: Programming Language :: Python :: 3.6
Classifier: Programming Language :: Python :: 3.7
Classifier: Programming Language :: Python :: 3.8
Classifier: Programming Language :: Python :: 3.9
Classifier: Programming Language :: Python :: 3.10
Classifier: Programming Language :: Python :: 3 :: Only
Classifier: Environment :: Console
Requires-Python: >=3.6, <4
Requires-Dist: pyyaml
Provides-Extra: dev
Requires-Dist: check-manifest ; extra == 'dev'
